[
    {
        "stock": "$TLT",
        "type": "\ud83d\udd34P",
        "strike": "$98.0",
        "exp": "03/21/25",
        "gatherdate": "2025-03-07 10:42:53",
        "contractsymbol": "TLT250321P00098000",
        "stk_price": 90.94,
        "lastprice": 7.6,
        "ask": 7.35,
        "bid": 7.25,
        "change": 0.0,
        "percentchange": 0.0,
        "volume": 2253,
        "openinterest": 27,
        "impliedvolatility": 0.29688203124999996,
        "stk_price_chg": 0.45000000000000284,
        "stk_price_avg_30d": 90.7,
        "stk_price_avg_5d": 90.7,
        "lastprice_chg": 0.04999999999999982,
        "lastprice_avg_30d": 7.373333333333332,
        "lastprice_avg_5d": 7.373333333333332,
        "pct_chg": 0.6622516556291367,
        "iv_chg": 0.29687203124999995,
        "iv_avg_5d": 0.09896734374999999,
        "iv_avg_30d": 0.09896734374999999,
        "iv_avg_all": 0.09896734374999999,
        "vol_chg": 2231.0,
        "oi_chg": -363.0,
        "flag": 0,
        "amnt": 0,
        "voi": 83,
        "flag_name": "voi",
        "moneyness": 0.9279591836734694
    },
    {
        "stock": "$TLT",
        "type": "\ud83d\udd34P",
        "strike": "$94.0",
        "exp": "03/07/25",
        "gatherdate": "2025-03-07 10:42:53",
        "contractsymbol": "TLT250307P00094000",
        "stk_price": 90.94,
        "lastprice": 3.6,
        "ask": 3.3,
        "bid": 3.2,
        "change": 0.0,
        "percentchange": 0.0,
        "volume": 2017,
        "openinterest": 61,
        "impliedvolatility": 0.57617611328125,
        "stk_price_chg": 0.45000000000000284,
        "stk_price_avg_30d": 90.7,
        "stk_price_avg_5d": 90.7,
        "lastprice_chg": -0.31000000000000005,
        "lastprice_avg_30d": 3.47,
        "lastprice_avg_5d": 3.47,
        "pct_chg": -7.928388746803069,
        "iv_chg": 0.57616611328125,
        "iv_avg_5d": 0.19206537109375,
        "iv_avg_30d": 0.19206537109375,
        "iv_avg_all": 0.19206537109375,
        "vol_chg": 2000.0,
        "oi_chg": -9205.0,
        "flag": 0,
        "amnt": 0,
        "voi": 33,
        "flag_name": "voi",
        "moneyness": 0.9674468085106382
    },
    {
        "stock": "$NVDA",
        "type": "\ud83d\udfe2C",
        "strike": "$139.0",
        "exp": "04/11/25",
        "gatherdate": "2025-03-07 10:44:55",
        "contractsymbol": "NVDA250411C00139000",
        "stk_price": 110.59,
        "lastprice": 1.02,
        "ask": 1.03,
        "bid": 0.99,
        "change": 0.01999998,
        "percentchange": 1.9999981,
        "volume": 2044,
        "openinterest": 96,
        "impliedvolatility": 0.5625043750000001,
        "stk_price_chg": -1.4699999999999989,
        "stk_price_avg_30d": 113.37666666666667,
        "stk_price_avg_5d": 113.37666666666667,
        "lastprice_chg": -0.1299999999999999,
        "lastprice_avg_30d": 1.3433333333333335,
        "lastprice_avg_5d": 1.3433333333333335,
        "pct_chg": -11.304347826086948,
        "iv_chg": 0.027099338378906213,
        "iv_avg_5d": 0.543298837890625,
        "iv_avg_30d": 0.543298837890625,
        "iv_avg_all": 0.543298837890625,
        "vol_chg": 2040.0,
        "oi_chg": 1.0,
        "flag": 0,
        "amnt": 0,
        "voi": 21,
        "flag_name": "voi",
        "moneyness": 0.7956115107913669
    },
    {
        "stock": "$ENPH",
        "type": "\ud83d\udfe2C",
        "strike": "$71.0",
        "exp": "03/14/25",
        "gatherdate": "2025-03-07 10:33:51",
        "contractsymbol": "ENPH250314C00071000",
        "stk_price": 62.31,
        "lastprice": 0.23,
        "ask": 0.32,
        "bid": 0.28,
        "change": 0.049999997,
        "percentchange": 27.777775,
        "volume": 1107,
        "openinterest": 63,
        "impliedvolatility": 0.6718782812500002,
        "stk_price_chg": 3.6000000000000014,
        "stk_price_avg_30d": 59.76,
        "stk_price_avg_5d": 59.76,
        "lastprice_chg": 0.05000000000000002,
        "lastprice_avg_30d": 0.19666666666666666,
        "lastprice_avg_5d": 0.19666666666666666,
        "pct_chg": 27.77777777777779,
        "iv_chg": -0.019531054687499938,
        "iv_avg_5d": 0.6770865625000001,
        "iv_avg_30d": 0.6770865625000001,
        "iv_avg_all": 0.6770865625000001,
        "vol_chg": 1098.0,
        "oi_chg": 0.0,
        "flag": 0,
        "amnt": 0,
        "voi": 17,
        "flag_name": "voi",
        "moneyness": 0.877605633802817
    },
    {
        "stock": "$SPY",
        "type": "\ud83d\udfe2C",
        "strike": "$582.0",
        "exp": "03/28/25",
        "gatherdate": "2025-03-07 10:29:15",
        "contractsymbol": "SPY250328C00582000",
        "stk_price": 572.23,
        "lastprice": 8.33,
        "ask": 7.99,
        "bid": 7.93,
        "change": 0.3499999,
        "percentchange": 4.385964,
        "volume": 4161,
        "openinterest": 247,
        "impliedvolatility": 0.21726246612548827,
        "stk_price_chg": 1.6000000000000227,
        "stk_price_avg_30d": 575.5033333333333,
        "stk_price_avg_5d": 575.5033333333333,
        "lastprice_chg": 1.08,
        "lastprice_avg_30d": 8.573333333333332,
        "lastprice_avg_5d": 8.573333333333332,
        "pct_chg": 14.896551724137932,
        "iv_chg": 0.002899140930175792,
        "iv_avg_5d": 0.19555451263427734,
        "iv_avg_30d": 0.19555451263427734,
        "iv_avg_all": 0.19555451263427734,
        "vol_chg": 4008.0,
        "oi_chg": -14.0,
        "flag": 0,
        "amnt": 0,
        "voi": 16,
        "flag_name": "voi",
        "moneyness": 0.983213058419244
    },
    {
        "stock": "$OKLO",
        "type": "\ud83d\udfe2C",
        "strike": "$27.0",
        "exp": "03/07/25",
        "gatherdate": "2025-03-07 10:56:44",
        "contractsymbol": "OKLO250307C00027000",
        "stk_price": 25.15,
        "lastprice": 0.2,
        "ask": 0.22,
        "bid": 0.16,
        "change": -0.21999998,
        "percentchange": -52.38095,
        "volume": 1469,
        "openinterest": 109,
        "impliedvolatility": 1.4609401953124999,
        "stk_price_chg": -0.7200000000000024,
        "stk_price_avg_30d": 27.106666666666666,
        "stk_price_avg_5d": 27.106666666666666,
        "lastprice_chg": -0.39999999999999997,
        "lastprice_avg_30d": 1.5266666666666666,
        "lastprice_avg_5d": 1.5266666666666666,
        "pct_chg": -66.66666666666666,
        "iv_chg": 0.15038987304687512,
        "iv_avg_5d": 1.126956474609375,
        "iv_avg_30d": 1.126956474609375,
        "iv_avg_all": 1.126956474609375,
        "vol_chg": 1392.0,
        "oi_chg": 89.0,
        "flag": 1,
        "amnt": 12,
        "voi": 13,
        "flag_name": "voi",
        "moneyness": 0.9314814814814815
    },
    {
        "stock": "$NVDA",
        "type": "\ud83d\udfe2C",
        "strike": "$134.0",
        "exp": "04/11/25",
        "gatherdate": "2025-03-07 10:44:55",
        "contractsymbol": "NVDA250411C00134000",
        "stk_price": 110.59,
        "lastprice": 1.57,
        "ask": 1.53,
        "bid": 1.49,
        "change": 0.0200001,
        "percentchange": 1.2903291,
        "volume": 2016,
        "openinterest": 174,
        "impliedvolatility": 0.5620160986328125,
        "stk_price_chg": -1.4699999999999989,
        "stk_price_avg_30d": 113.37666666666667,
        "stk_price_avg_5d": 113.37666666666667,
        "lastprice_chg": 0.020000000000000018,
        "lastprice_avg_30d": 1.96,
        "lastprice_avg_5d": 1.96,
        "pct_chg": 1.2903225806451624,
        "iv_chg": 0.03210417114257813,
        "iv_avg_5d": 0.5426884924316407,
        "iv_avg_30d": 0.5426884924316407,
        "iv_avg_all": 0.5426884924316407,
        "vol_chg": 1984.0,
        "oi_chg": 15.0,
        "flag": 0,
        "amnt": 0,
        "voi": 11,
        "flag_name": "voi",
        "moneyness": 0.8252985074626866
    },
    {
        "stock": "$AAL",
        "type": "\ud83d\udfe2C",
        "strike": "$13.0",
        "exp": "03/07/25",
        "gatherdate": "2025-03-07 10:30:02",
        "contractsymbol": "AAL250307C00013000",
        "stk_price": 13.01,
        "lastprice": 0.18,
        "ask": 0.18,
        "bid": 0.17,
        "change": -0.25,
        "percentchange": -58.139534,
        "volume": 2881,
        "openinterest": 284,
        "impliedvolatility": 0.6445348046875,
        "stk_price_chg": -0.370000000000001,
        "stk_price_avg_30d": 13.526666666666666,
        "stk_price_avg_5d": 13.526666666666666,
        "lastprice_chg": -0.45,
        "lastprice_avg_30d": 0.62,
        "lastprice_avg_5d": 0.62,
        "pct_chg": -71.42857142857143,
        "iv_chg": -0.08203042968749996,
        "iv_avg_5d": 0.4570366796875,
        "iv_avg_30d": 0.4570366796875,
        "iv_avg_all": 0.4570366796875,
        "vol_chg": 2844.0,
        "oi_chg": 86.0,
        "flag": 1,
        "amnt": 49,
        "voi": 10,
        "flag_name": "voi",
        "moneyness": 1.0007692307692309
    },
    {
        "stock": "$QQQ",
        "type": "\ud83d\udfe2C",
        "strike": "$491.0",
        "exp": "03/07/25",
        "gatherdate": "2025-03-07 10:37:52",
        "contractsymbol": "QQQ250307C00491000",
        "stk_price": 484.48,
        "lastprice": 2.82,
        "ask": 2.81,
        "bid": 2.79,
        "change": -1.0800002,
        "percentchange": -27.69231,
        "volume": 16845,
        "openinterest": 1994,
        "impliedvolatility": 0.5366257275390626,
        "stk_price_chg": -3.6399999999999864,
        "stk_price_avg_30d": 491.42333333333335,
        "stk_price_avg_5d": 491.42333333333335,
        "lastprice_chg": -1.0300000000000002,
        "lastprice_avg_30d": 5.573333333333333,
        "lastprice_avg_5d": 5.573333333333333,
        "pct_chg": -26.753246753246756,
        "iv_chg": 0.18725398681640637,
        "iv_avg_5d": 0.35938140625000004,
        "iv_avg_30d": 0.35938140625000004,
        "iv_avg_all": 0.35938140625000004,
        "vol_chg": 7879.0,
        "oi_chg": 851.0,
        "flag": 0,
        "amnt": 0,
        "voi": 8,
        "flag_name": "voi",
        "moneyness": 0.9867209775967414
    },
    {
        "stock": "$AMD",
        "type": "\ud83d\udd34P",
        "strike": "$60.0",
        "exp": "08/15/25",
        "gatherdate": "2025-03-07 10:40:30",
        "contractsymbol": "AMD250815P00060000",
        "stk_price": 97.99,
        "lastprice": 1.03,
        "ask": 1.05,
        "bid": 1.02,
        "change": -0.120000005,
        "percentchange": -10.434783,
        "volume": 1092,
        "openinterest": 127,
        "impliedvolatility": 0.5336960693359375,
        "stk_price_chg": -1.2600000000000051,
        "stk_price_avg_30d": 99.58666666666666,
        "stk_price_avg_5d": 99.58666666666666,
        "lastprice_chg": 0.020000000000000018,
        "lastprice_avg_30d": 1.0166666666666666,
        "lastprice_avg_5d": 1.0166666666666666,
        "pct_chg": 1.980198019801982,
        "iv_chg": -0.021240021972656398,
        "iv_avg_5d": 0.5465540136718751,
        "iv_avg_30d": 0.5465540136718751,
        "iv_avg_all": 0.5465540136718751,
        "vol_chg": 1089.0,
        "oi_chg": 1.0,
        "flag": 0,
        "amnt": 0,
        "voi": 8,
        "flag_name": "voi",
        "moneyness": 1.6331666666666667
    },
    {
        "stock": "$SPY",
        "type": "\ud83d\udfe2C",
        "strike": "$576.0",
        "exp": "03/07/25",
        "gatherdate": "2025-03-07 10:29:15",
        "contractsymbol": "SPY250307C00576000",
        "stk_price": 572.23,
        "lastprice": 2.36,
        "ask": 2.37,
        "bid": 2.36,
        "change": -1.24,
        "percentchange": -34.444447,
        "volume": 33020,
        "openinterest": 4817,
        "impliedvolatility": 0.33301448242187504,
        "stk_price_chg": 1.6000000000000227,
        "stk_price_avg_30d": 575.5033333333333,
        "stk_price_avg_5d": 575.5033333333333,
        "lastprice_chg": -0.7200000000000002,
        "lastprice_avg_30d": 4.226666666666667,
        "lastprice_avg_5d": 4.226666666666667,
        "pct_chg": -23.37662337662338,
        "iv_chg": 0.019286916503906293,
        "iv_avg_5d": 0.21558401611328126,
        "iv_avg_30d": 0.21558401611328126,
        "iv_avg_all": 0.21558401611328126,
        "vol_chg": 11511.0,
        "oi_chg": 1778.0,
        "flag": 0,
        "amnt": 0,
        "voi": 6,
        "flag_name": "voi",
        "moneyness": 0.9934548611111111
    },
    {
        "stock": "$RKT",
        "type": "\ud83d\udfe2C",
        "strike": "$15.0",
        "exp": "03/14/25",
        "gatherdate": "2025-03-07 10:37:36",
        "contractsymbol": "RKT250314C00015000",
        "stk_price": 15.49,
        "lastprice": 1.0,
        "ask": 1.0,
        "bid": 0.95,
        "change": 0.5,
        "percentchange": 102.04082,
        "volume": 2644,
        "openinterest": 398,
        "impliedvolatility": 0.7812521875,
        "stk_price_chg": 0.8399999999999999,
        "stk_price_avg_30d": 14.976666666666667,
        "stk_price_avg_5d": 14.976666666666667,
        "lastprice_chg": 0.5900000000000001,
        "lastprice_avg_30d": 0.62,
        "lastprice_avg_5d": 0.62,
        "pct_chg": 143.90243902439028,
        "iv_chg": 0.12695185546874987,
        "iv_avg_5d": 0.65560240234375,
        "iv_avg_30d": 0.65560240234375,
        "iv_avg_all": 0.65560240234375,
        "vol_chg": 2624.0,
        "oi_chg": -4.0,
        "flag": 0,
        "amnt": 0,
        "voi": 6,
        "flag_name": "voi",
        "moneyness": 1.0326666666666666
    },
    {
        "stock": "$QQQ",
        "type": "\ud83d\udfe2C",
        "strike": "$491.0",
        "exp": "03/10/25",
        "gatherdate": "2025-03-07 10:37:52",
        "contractsymbol": "QQQ250310C00491000",
        "stk_price": 484.48,
        "lastprice": 4.69,
        "ask": 4.75,
        "bid": 4.73,
        "change": -0.8800001,
        "percentchange": -15.742399,
        "volume": 3659,
        "openinterest": 561,
        "impliedvolatility": 0.3723207299804688,
        "stk_price_chg": -3.6399999999999864,
        "stk_price_avg_30d": 491.42333333333335,
        "stk_price_avg_5d": 491.42333333333335,
        "lastprice_chg": -0.5999999999999996,
        "lastprice_avg_30d": 7.260000000000001,
        "lastprice_avg_5d": 7.260000000000001,
        "pct_chg": -11.342155009451789,
        "iv_chg": 0.09020905883789071,
        "iv_avg_5d": 0.28247787841796873,
        "iv_avg_30d": 0.28247787841796873,
        "iv_avg_all": 0.28247787841796873,
        "vol_chg": 3063.0,
        "oi_chg": 168.0,
        "flag": 0,
        "amnt": 0,
        "voi": 6,
        "flag_name": "voi",
        "moneyness": 0.9867209775967414
    },
    {
        "stock": "$TTD",
        "type": "\ud83d\udfe2C",
        "strike": "$73.0",
        "exp": "03/14/25",
        "gatherdate": "2025-03-07 10:53:50",
        "contractsymbol": "TTD250314C00073000",
        "stk_price": 65.84,
        "lastprice": 0.29,
        "ask": 0.31,
        "bid": 0.29,
        "change": 0.0,
        "percentchange": 0.0,
        "volume": 1267,
        "openinterest": 207,
        "impliedvolatility": 0.5634809277343751,
        "stk_price_chg": 0.7000000000000028,
        "stk_price_avg_30d": 65.57000000000001,
        "stk_price_avg_5d": 65.57000000000001,
        "lastprice_chg": 0.0,
        "lastprice_avg_30d": 0.32,
        "lastprice_avg_5d": 0.32,
        "pct_chg": 0.0,
        "iv_chg": 0.002929658203125074,
        "iv_avg_5d": 0.5642947216796875,
        "iv_avg_30d": 0.5642947216796875,
        "iv_avg_all": 0.5642947216796875,
        "vol_chg": 1169.0,
        "oi_chg": 7.0,
        "flag": 0,
        "amnt": 0,
        "voi": 6,
        "flag_name": "voi",
        "moneyness": 0.9019178082191781
    },
    {
        "stock": "$QQQ",
        "type": "\ud83d\udfe2C",
        "strike": "$493.0",
        "exp": "03/10/25",
        "gatherdate": "2025-03-07 10:37:52",
        "contractsymbol": "QQQ250310C00493000",
        "stk_price": 484.48,
        "lastprice": 3.79,
        "ask": 3.79,
        "bid": 3.76,
        "change": -0.8499999,
        "percentchange": -18.318964,
        "volume": 2850,
        "openinterest": 552,
        "impliedvolatility": 0.3569400244140625,
        "stk_price_chg": -3.6399999999999864,
        "stk_price_avg_30d": 491.42333333333335,
        "stk_price_avg_5d": 491.42333333333335,
        "lastprice_chg": -0.45999999999999996,
        "lastprice_avg_30d": 5.986666666666667,
        "lastprice_avg_5d": 5.986666666666667,
        "pct_chg": -10.823529411764705,
        "iv_chg": 0.07299731689453132,
        "iv_avg_5d": 0.2832916723632812,
        "iv_avg_30d": 0.2832916723632812,
        "iv_avg_all": 0.2832916723632812,
        "vol_chg": 959.0,
        "oi_chg": 320.0,
        "flag": 0,
        "amnt": 0,
        "voi": 5,
        "flag_name": "voi",
        "moneyness": 0.9827180527383368
    },
    {
        "stock": "$QQQ",
        "type": "\ud83d\udd34P",
        "strike": "$473.0",
        "exp": "03/10/25",
        "gatherdate": "2025-03-07 10:37:52",
        "contractsymbol": "QQQ250310P00473000",
        "stk_price": 484.48,
        "lastprice": 0.73,
        "ask": 0.55,
        "bid": 0.54,
        "change": -0.56999993,
        "percentchange": -43.84615,
        "volume": 3777,
        "openinterest": 713,
        "impliedvolatility": 0.19178054321289065,
        "stk_price_chg": -3.6399999999999864,
        "stk_price_avg_30d": 491.42333333333335,
        "stk_price_avg_5d": 491.42333333333335,
        "lastprice_chg": -0.8999999999999999,
        "lastprice_avg_30d": 1.0866666666666667,
        "lastprice_avg_5d": 1.0866666666666667,
        "pct_chg": -55.21472392638037,
        "iv_chg": -0.10339252075195307,
        "iv_avg_5d": 0.2676261389160156,
        "iv_avg_30d": 0.2676261389160156,
        "iv_avg_all": 0.2676261389160156,
        "vol_chg": 3305.0,
        "oi_chg": 168.0,
        "flag": 0,
        "amnt": 0,
        "voi": 5,
        "flag_name": "voi",
        "moneyness": 1.0242706131078225
    },
    {
        "stock": "$XLE",
        "type": "\ud83d\udfe2C",
        "strike": "$87.5",
        "exp": "03/14/25",
        "gatherdate": "2025-03-07 10:40:44",
        "contractsymbol": "XLE250314C00087500",
        "stk_price": 87.32,
        "lastprice": 1.5,
        "ask": 1.66,
        "bid": 1.62,
        "change": 0.40999997,
        "percentchange": 37.614674,
        "volume": 1839,
        "openinterest": 346,
        "impliedvolatility": 0.3415593188476562,
        "stk_price_chg": 1.25,
        "stk_price_avg_30d": 86.36,
        "stk_price_avg_5d": 86.36,
        "lastprice_chg": 0.68,
        "lastprice_avg_30d": 1.0366666666666666,
        "lastprice_avg_5d": 1.0366666666666666,
        "pct_chg": 82.92682926829269,
        "iv_chg": 0.054198676757812536,
        "iv_avg_5d": 0.3038806591796875,
        "iv_avg_30d": 0.3038806591796875,
        "iv_avg_all": 0.3038806591796875,
        "vol_chg": 1815.0,
        "oi_chg": 22.0,
        "flag": 0,
        "amnt": 0,
        "voi": 5,
        "flag_name": "voi",
        "moneyness": 0.997942857142857
    },
    {
        "stock": "$LQD",
        "type": "\ud83d\udd34P",
        "strike": "$104.0",
        "exp": "05/16/25",
        "gatherdate": "2025-03-07 10:42:23",
        "contractsymbol": "LQD250516P00104000",
        "stk_price": 108.84,
        "lastprice": 0.19,
        "ask": 0.32,
        "bid": 0.24,
        "change": 0.0,
        "percentchange": 0.0,
        "volume": 5020,
        "openinterest": 845,
        "impliedvolatility": 0.09546802978515626,
        "stk_price_chg": 0.3299999999999983,
        "stk_price_avg_30d": 108.74666666666667,
        "stk_price_avg_5d": 108.74666666666667,
        "lastprice_chg": 0.0,
        "lastprice_avg_30d": 0.19000000000000003,
        "lastprice_avg_5d": 0.19000000000000003,
        "pct_chg": 0.0,
        "iv_chg": 0.0039062109375000154,
        "iv_avg_5d": 0.09237561279296876,
        "iv_avg_30d": 0.09237561279296876,
        "iv_avg_all": 0.09237561279296876,
        "vol_chg": 0.0,
        "oi_chg": 0.0,
        "flag": 0,
        "amnt": 0,
        "voi": 5,
        "flag_name": "voi",
        "moneyness": 1.0465384615384616
    },
    {
        "stock": "$GLD",
        "type": "\ud83d\udfe2C",
        "strike": "$278.0",
        "exp": "03/14/25",
        "gatherdate": "2025-03-07 10:49:25",
        "contractsymbol": "GLD250314C00278000",
        "stk_price": 268.61,
        "lastprice": 0.3,
        "ask": 0.31,
        "bid": 0.3,
        "change": 0.0,
        "percentchange": 0.0,
        "volume": 1482,
        "openinterest": 253,
        "impliedvolatility": 0.174812939453125,
        "stk_price_chg": -0.39999999999997726,
        "stk_price_avg_30d": 268.9433333333333,
        "stk_price_avg_5d": 268.9433333333333,
        "lastprice_chg": -0.07,
        "lastprice_avg_30d": 0.36999999999999994,
        "lastprice_avg_5d": 0.36999999999999994,
        "pct_chg": -18.91891891891892,
        "iv_chg": 0.013183461914062528,
        "iv_avg_5d": 0.1674887939453125,
        "iv_avg_30d": 0.1674887939453125,
        "iv_avg_all": 0.1674887939453125,
        "vol_chg": 1476.0,
        "oi_chg": 2.0,
        "flag": 0,
        "amnt": 0,
        "voi": 5,
        "flag_name": "voi",
        "moneyness": 0.9662230215827339
    },
    {
        "stock": "$SPY",
        "type": "\ud83d\udfe2C",
        "strike": "$572.0",
        "exp": "03/07/25",
        "gatherdate": "2025-03-07 10:29:15",
        "contractsymbol": "SPY250307C00572000",
        "stk_price": 572.23,
        "lastprice": 4.6,
        "ask": 4.6,
        "bid": 4.59,
        "change": -1.1300001,
        "percentchange": -19.72077,
        "volume": 19192,
        "openinterest": 4516,
        "impliedvolatility": 0.37744763183593744,
        "stk_price_chg": 1.6000000000000227,
        "stk_price_avg_30d": 575.5033333333333,
        "stk_price_avg_5d": 575.5033333333333,
        "lastprice_chg": -0.1800000000000006,
        "lastprice_avg_30d": 6.6000000000000005,
        "lastprice_avg_5d": 6.6000000000000005,
        "pct_chg": -3.7656903765690504,
        "iv_chg": 0.055297298583984356,
        "iv_avg_5d": 0.23320265502929682,
        "iv_avg_30d": 0.23320265502929682,
        "iv_avg_all": 0.23320265502929682,
        "vol_chg": 6470.0,
        "oi_chg": 3790.0,
        "flag": 0,
        "amnt": 0,
        "voi": 4,
        "flag_name": "voi",
        "moneyness": 1.000402097902098
    },
    {
        "stock": "$SPY",
        "type": "\ud83d\udfe2C",
        "strike": "$573.0",
        "exp": "03/07/25",
        "gatherdate": "2025-03-07 10:29:15",
        "contractsymbol": "SPY250307C00573000",
        "stk_price": 572.23,
        "lastprice": 4.05,
        "ask": 4.05,
        "bid": 4.04,
        "change": -1.0799999,
        "percentchange": -21.093748,
        "volume": 24373,
        "openinterest": 5085,
        "impliedvolatility": 0.372076591796875,
        "stk_price_chg": 1.6000000000000227,
        "stk_price_avg_30d": 575.5033333333333,
        "stk_price_avg_5d": 575.5033333333333,
        "lastprice_chg": -0.16000000000000014,
        "lastprice_avg_30d": 6.073333333333333,
        "lastprice_avg_5d": 6.073333333333333,
        "pct_chg": -3.8004750593824266,
        "iv_chg": 0.05529729858398447,
        "iv_avg_5d": 0.22962196166992185,
        "iv_avg_30d": 0.22962196166992185,
        "iv_avg_all": 0.22962196166992185,
        "vol_chg": 2512.0,
        "oi_chg": 4393.0,
        "flag": 0,
        "amnt": 0,
        "voi": 4,
        "flag_name": "voi",
        "moneyness": 0.9986561954624782
    },
    {
        "stock": "$SPY",
        "type": "\ud83d\udfe2C",
        "strike": "$574.0",
        "exp": "03/07/25",
        "gatherdate": "2025-03-07 10:29:15",
        "contractsymbol": "SPY250307C00574000",
        "stk_price": 572.23,
        "lastprice": 3.39,
        "ask": 3.43,
        "bid": 3.42,
        "change": -1.2099998,
        "percentchange": -26.304344,
        "volume": 26861,
        "openinterest": 5964,
        "impliedvolatility": 0.3575503698730469,
        "stk_price_chg": 1.6000000000000227,
        "stk_price_avg_30d": 575.5033333333333,
        "stk_price_avg_5d": 575.5033333333333,
        "lastprice_chg": -0.2999999999999998,
        "lastprice_avg_30d": 5.333333333333333,
        "lastprice_avg_5d": 5.333333333333333,
        "pct_chg": -8.130081300813004,
        "iv_chg": 0.043090389404296936,
        "iv_avg_5d": 0.22400678344726563,
        "iv_avg_30d": 0.22400678344726563,
        "iv_avg_all": 0.22400678344726563,
        "vol_chg": 8048.0,
        "oi_chg": 5018.0,
        "flag": 0,
        "amnt": 0,
        "voi": 4,
        "flag_name": "voi",
        "moneyness": 0.9969163763066202
    },
    {
        "stock": "$TSLA",
        "type": "\ud83d\udfe2C",
        "strike": "$262.5",
        "exp": "03/07/25",
        "gatherdate": "2025-03-07 10:35:42",
        "contractsymbol": "TSLA250307C00262500",
        "stk_price": 258.44,
        "lastprice": 4.3,
        "ask": 4.35,
        "bid": 4.25,
        "change": -1.75,
        "percentchange": -28.92562,
        "volume": 8759,
        "openinterest": 1966,
        "impliedvolatility": 1.1469769213867185,
        "stk_price_chg": -3.980000000000018,
        "stk_price_avg_30d": 266.51666666666665,
        "stk_price_avg_5d": 266.51666666666665,
        "lastprice_chg": -1.6000000000000005,
        "lastprice_avg_30d": 8.15,
        "lastprice_avg_5d": 8.15,
        "pct_chg": -27.118644067796616,
        "iv_chg": 0.3774433666992184,
        "iv_avg_5d": 0.6388401586914062,
        "iv_avg_30d": 0.6388401586914062,
        "iv_avg_all": 0.6388401586914062,
        "vol_chg": -3347.0,
        "oi_chg": 1083.0,
        "flag": 0,
        "amnt": 0,
        "voi": 4,
        "flag_name": "voi",
        "moneyness": 0.9845333333333334
    },
    {
        "stock": "$TSLA",
        "type": "\ud83d\udfe2C",
        "strike": "$265.0",
        "exp": "03/07/25",
        "gatherdate": "2025-03-07 10:35:42",
        "contractsymbol": "TSLA250307C00265000",
        "stk_price": 258.44,
        "lastprice": 3.05,
        "ask": 3.05,
        "bid": 3.0,
        "change": -1.8,
        "percentchange": -37.113403,
        "volume": 33505,
        "openinterest": 6809,
        "impliedvolatility": 1.0654343603515626,
        "stk_price_chg": -3.980000000000018,
        "stk_price_avg_30d": 266.51666666666665,
        "stk_price_avg_5d": 266.51666666666665,
        "lastprice_chg": -1.7999999999999998,
        "lastprice_avg_30d": 6.949999999999999,
        "lastprice_avg_5d": 6.949999999999999,
        "pct_chg": -37.11340206185567,
        "iv_chg": 0.27881113281250014,
        "iv_avg_5d": 0.6173558626302084,
        "iv_avg_30d": 0.6173558626302084,
        "iv_avg_all": 0.6173558626302084,
        "vol_chg": -1125.0,
        "oi_chg": 4392.0,
        "flag": 0,
        "amnt": 0,
        "voi": 4,
        "flag_name": "voi",
        "moneyness": 0.9752452830188679
    },
    {
        "stock": "$QQQ",
        "type": "\ud83d\udfe2C",
        "strike": "$488.0",
        "exp": "03/07/25",
        "gatherdate": "2025-03-07 10:37:52",
        "contractsymbol": "QQQ250307C00488000",
        "stk_price": 484.48,
        "lastprice": 4.5,
        "ask": 4.53,
        "bid": 4.49,
        "change": -0.88999987,
        "percentchange": -16.512056,
        "volume": 11798,
        "openinterest": 2362,
        "impliedvolatility": 0.6033975207519533,
        "stk_price_chg": -3.6399999999999864,
        "stk_price_avg_30d": 491.42333333333335,
        "stk_price_avg_5d": 491.42333333333335,
        "lastprice_chg": -0.6799999999999997,
        "lastprice_avg_30d": 7.8566666666666665,
        "lastprice_avg_5d": 7.8566666666666665,
        "pct_chg": -13.127413127413124,
        "iv_chg": 0.2488988781738284,
        "iv_avg_5d": 0.3193020544433594,
        "iv_avg_30d": 0.3193020544433594,
        "iv_avg_all": 0.3193020544433594,
        "vol_chg": 7485.0,
        "oi_chg": 2010.0,
        "flag": 0,
        "amnt": 0,
        "voi": 4,
        "flag_name": "voi",
        "moneyness": 0.9927868852459016
    },
    {
        "stock": "$XLE",
        "type": "\ud83d\udfe2C",
        "strike": "$88.0",
        "exp": "03/07/25",
        "gatherdate": "2025-03-07 10:40:44",
        "contractsymbol": "XLE250307C00088000",
        "stk_price": 87.32,
        "lastprice": 0.3,
        "ask": 0.35,
        "bid": 0.32,
        "change": 0.15,
        "percentchange": 100.0,
        "volume": 1065,
        "openinterest": 247,
        "impliedvolatility": 0.35156898437499995,
        "stk_price_chg": 1.25,
        "stk_price_avg_30d": 86.36,
        "stk_price_avg_5d": 86.36,
        "lastprice_chg": 0.16999999999999998,
        "lastprice_avg_30d": 0.20666666666666667,
        "lastprice_avg_5d": 0.20666666666666667,
        "pct_chg": 130.76923076923075,
        "iv_chg": 0.058593164062500036,
        "iv_avg_5d": 0.31576205078124997,
        "iv_avg_30d": 0.31576205078124997,
        "iv_avg_all": 0.31576205078124997,
        "vol_chg": 1024.0,
        "oi_chg": 17.0,
        "flag": 0,
        "amnt": 0,
        "voi": 4,
        "flag_name": "voi",
        "moneyness": 0.9922727272727272
    },
    {
        "stock": "$IWM",
        "type": "\ud83d\udd34P",
        "strike": "$200.0",
        "exp": "03/12/25",
        "gatherdate": "2025-03-07 10:48:16",
        "contractsymbol": "IWM250312P00200000",
        "stk_price": 203.58,
        "lastprice": 1.18,
        "ask": 1.37,
        "bid": 1.35,
        "change": -0.42000008,
        "percentchange": -26.250004,
        "volume": 1557,
        "openinterest": 369,
        "impliedvolatility": 0.27173579833984374,
        "stk_price_chg": -2.4099999999999966,
        "stk_price_avg_30d": 205.9666666666667,
        "stk_price_avg_5d": 205.9666666666667,
        "lastprice_chg": -0.8200000000000001,
        "lastprice_avg_30d": 1.5599999999999998,
        "lastprice_avg_5d": 1.5599999999999998,
        "pct_chg": -41.0,
        "iv_chg": -0.12695185546875004,
        "iv_avg_5d": 0.34131518066406247,
        "iv_avg_30d": 0.34131518066406247,
        "iv_avg_all": 0.34131518066406247,
        "vol_chg": 1165.0,
        "oi_chg": 80.0,
        "flag": 0,
        "amnt": 0,
        "voi": 4,
        "flag_name": "voi",
        "moneyness": 1.0179
    },
    {
        "stock": "$AVGO",
        "type": "\ud83d\udfe2C",
        "strike": "$192.5",
        "exp": "03/07/25",
        "gatherdate": "2025-03-07 10:52:48",
        "contractsymbol": "AVGO250307C00192500",
        "stk_price": 184.54,
        "lastprice": 0.65,
        "ask": 0.65,
        "bid": 0.61,
        "change": -2.65,
        "percentchange": -79.10448,
        "volume": 12681,
        "openinterest": 3077,
        "impliedvolatility": 0.7939473730468749,
        "stk_price_chg": 4.789999999999992,
        "stk_price_avg_30d": 185.79333333333332,
        "stk_price_avg_5d": 185.79333333333332,
        "lastprice_chg": -2.85,
        "lastprice_avg_30d": 4.333333333333333,
        "lastprice_avg_5d": 4.333333333333333,
        "pct_chg": -81.42857142857143,
        "iv_chg": -0.7324221826171873,
        "iv_avg_5d": 1.169273663736979,
        "iv_avg_30d": 1.169273663736979,
        "iv_avg_all": 1.169273663736979,
        "vol_chg": 9272.0,
        "oi_chg": 503.0,
        "flag": 0,
        "amnt": 0,
        "voi": 4,
        "flag_name": "voi",
        "moneyness": 0.9586493506493506
    },
    {
        "stock": "$ENPH",
        "type": "\ud83d\udd34P",
        "strike": "$60.0",
        "exp": "03/07/25",
        "gatherdate": "2025-03-07 10:33:51",
        "contractsymbol": "ENPH250307P00060000",
        "stk_price": 62.31,
        "lastprice": 0.31,
        "ask": 0.29,
        "bid": 0.22,
        "change": -1.73,
        "percentchange": -84.803925,
        "volume": 1090,
        "openinterest": 300,
        "impliedvolatility": 0.8125018749999999,
        "stk_price_chg": 3.6000000000000014,
        "stk_price_avg_30d": 59.76,
        "stk_price_avg_5d": 59.76,
        "lastprice_chg": -1.75,
        "lastprice_avg_30d": 2.14,
        "lastprice_avg_5d": 2.14,
        "pct_chg": -84.9514563106796,
        "iv_chg": -0.10546769531250011,
        "iv_avg_5d": 0.9189478336588541,
        "iv_avg_30d": 0.9189478336588541,
        "iv_avg_all": 0.9189478336588541,
        "vol_chg": 1062.0,
        "oi_chg": -16.0,
        "flag": 0,
        "amnt": 0,
        "voi": 3,
        "flag_name": "voi",
        "moneyness": 1.0385
    },
    {
        "stock": "$BABA",
        "type": "\ud83d\udd34P",
        "strike": "$142.0",
        "exp": "03/07/25",
        "gatherdate": "2025-03-07 10:35:08",
        "contractsymbol": "BABA250307P00142000",
        "stk_price": 142.76,
        "lastprice": 0.52,
        "ask": 0.46,
        "bid": 0.4,
        "change": -2.68,
        "percentchange": -83.75,
        "volume": 2245,
        "openinterest": 719,
        "impliedvolatility": 0.260749580078125,
        "stk_price_chg": 4.199999999999989,
        "stk_price_avg_30d": 140.67666666666665,
        "stk_price_avg_5d": 140.67666666666665,
        "lastprice_chg": -3.68,
        "lastprice_avg_30d": 2.9233333333333333,
        "lastprice_avg_5d": 2.9233333333333333,
        "pct_chg": -87.61904761904762,
        "iv_chg": -0.21484160156249998,
        "iv_avg_5d": 0.465174619140625,
        "iv_avg_30d": 0.465174619140625,
        "iv_avg_all": 0.465174619140625,
        "vol_chg": -1082.0,
        "oi_chg": 80.0,
        "flag": 0,
        "amnt": 0,
        "voi": 3,
        "flag_name": "voi",
        "moneyness": 1.0053521126760563
    },
    {
        "stock": "$TSLA",
        "type": "\ud83d\udfe2C",
        "strike": "$267.5",
        "exp": "03/07/25",
        "gatherdate": "2025-03-07 10:35:42",
        "contractsymbol": "TSLA250307C00267500",
        "stk_price": 258.44,
        "lastprice": 2.14,
        "ask": 2.2,
        "bid": 2.14,
        "change": -1.6699998,
        "percentchange": -44.772118,
        "volume": 13271,
        "openinterest": 3736,
        "impliedvolatility": 1.0307665649414064,
        "stk_price_chg": -3.980000000000018,
        "stk_price_avg_30d": 266.51666666666665,
        "stk_price_avg_5d": 266.51666666666665,
        "lastprice_chg": -1.63,
        "lastprice_avg_30d": 5.57,
        "lastprice_avg_5d": 5.57,
        "pct_chg": -43.236074270557026,
        "iv_chg": 0.2646509448242188,
        "iv_avg_5d": 0.598964061686198,
        "iv_avg_30d": 0.598964061686198,
        "iv_avg_all": 0.598964061686198,
        "vol_chg": -17385.0,
        "oi_chg": 2523.0,
        "flag": 0,
        "amnt": 0,
        "voi": 3,
        "flag_name": "voi",
        "moneyness": 0.9661308411214953
    },
    {
        "stock": "$TSLA",
        "type": "\ud83d\udfe2C",
        "strike": "$270.0",
        "exp": "03/07/25",
        "gatherdate": "2025-03-07 10:35:42",
        "contractsymbol": "TSLA250307C00270000",
        "stk_price": 258.44,
        "lastprice": 1.38,
        "ask": 1.39,
        "bid": 1.36,
        "change": -1.4799999,
        "percentchange": -51.74825,
        "volume": 38441,
        "openinterest": 9620,
        "impliedvolatility": 0.96679720703125,
        "stk_price_chg": -3.980000000000018,
        "stk_price_avg_30d": 266.51666666666665,
        "stk_price_avg_5d": 266.51666666666665,
        "lastprice_chg": -1.62,
        "lastprice_avg_30d": 4.760000000000001,
        "lastprice_avg_5d": 4.760000000000001,
        "pct_chg": -54.0,
        "iv_chg": 0.19433399414062502,
        "iv_avg_5d": 0.721031435546875,
        "iv_avg_30d": 0.721031435546875,
        "iv_avg_all": 0.721031435546875,
        "vol_chg": -25572.0,
        "oi_chg": 4911.0,
        "flag": 0,
        "amnt": 0,
        "voi": 3,
        "flag_name": "voi",
        "moneyness": 0.9571851851851851
    },
    {
        "stock": "$AMD",
        "type": "\ud83d\udfe2C",
        "strike": "$98.0",
        "exp": "03/14/25",
        "gatherdate": "2025-03-07 10:40:30",
        "contractsymbol": "AMD250314C00098000",
        "stk_price": 97.99,
        "lastprice": 3.25,
        "ask": 3.25,
        "bid": 3.2,
        "change": -0.25,
        "percentchange": -7.142857,
        "volume": 4482,
        "openinterest": 1227,
        "impliedvolatility": 0.5581098876953126,
        "stk_price_chg": -1.2600000000000051,
        "stk_price_avg_30d": 99.58666666666666,
        "stk_price_avg_5d": 99.58666666666666,
        "lastprice_chg": -0.2599999999999998,
        "lastprice_avg_30d": 3.8200000000000003,
        "lastprice_avg_5d": 3.8200000000000003,
        "pct_chg": -7.407407407407401,
        "iv_chg": 0.09399320068359379,
        "iv_avg_5d": 0.48787947021484374,
        "iv_avg_30d": 0.48787947021484374,
        "iv_avg_all": 0.48787947021484374,
        "vol_chg": 4313.0,
        "oi_chg": 31.0,
        "flag": 0,
        "amnt": 0,
        "voi": 3,
        "flag_name": "voi",
        "moneyness": 0.9998979591836734
    },
    {
        "stock": "$TLT",
        "type": "\ud83d\udfe2C",
        "strike": "$102.0",
        "exp": "07/31/25",
        "gatherdate": "2025-03-07 10:42:53",
        "contractsymbol": "TLT250731C00102000",
        "stk_price": 90.94,
        "lastprice": 0.64,
        "ask": 0.66,
        "bid": 0.63,
        "change": 0.0,
        "percentchange": 0.0,
        "volume": 10429,
        "openinterest": 2622,
        "impliedvolatility": 0.16211775390625,
        "stk_price_chg": 0.45000000000000284,
        "stk_price_avg_30d": 90.7,
        "stk_price_avg_5d": 90.7,
        "lastprice_chg": 0.0,
        "lastprice_avg_30d": 0.6866666666666666,
        "lastprice_avg_5d": 0.6866666666666666,
        "pct_chg": 0.0,
        "iv_chg": -0.006713800048828156,
        "iv_avg_5d": 0.16525086059570313,
        "iv_avg_30d": 0.16525086059570313,
        "iv_avg_all": 0.16525086059570313,
        "vol_chg": 0.0,
        "oi_chg": 0.0,
        "flag": 0,
        "amnt": 0,
        "voi": 3,
        "flag_name": "voi",
        "moneyness": 0.8915686274509804
    },
    {
        "stock": "$NVDA",
        "type": "\ud83d\udfe2C",
        "strike": "$112.0",
        "exp": "03/07/25",
        "gatherdate": "2025-03-07 10:44:55",
        "contractsymbol": "NVDA250307C00112000",
        "stk_price": 110.59,
        "lastprice": 1.43,
        "ask": 1.44,
        "bid": 1.43,
        "change": -0.07000005,
        "percentchange": -4.6666703,
        "volume": 46612,
        "openinterest": 14331,
        "impliedvolatility": 0.8867198828124999,
        "stk_price_chg": -1.4699999999999989,
        "stk_price_avg_30d": 113.37666666666667,
        "stk_price_avg_5d": 113.37666666666667,
        "lastprice_chg": -0.27,
        "lastprice_avg_30d": 3.14,
        "lastprice_avg_5d": 3.14,
        "pct_chg": -15.882352941176473,
        "iv_chg": 0.37743763183593737,
        "iv_avg_5d": 0.6798534619140625,
        "iv_avg_30d": 0.6798534619140625,
        "iv_avg_all": 0.6798534619140625,
        "vol_chg": 3414.0,
        "oi_chg": 8684.0,
        "flag": 0,
        "amnt": 0,
        "voi": 3,
        "flag_name": "voi",
        "moneyness": 0.9874107142857144
    },
    {
        "stock": "$NVDA",
        "type": "\ud83d\udfe2C",
        "strike": "$113.0",
        "exp": "03/07/25",
        "gatherdate": "2025-03-07 10:44:55",
        "contractsymbol": "NVDA250307C00113000",
        "stk_price": 110.59,
        "lastprice": 0.94,
        "ask": 0.94,
        "bid": 0.93,
        "change": -0.17000002,
        "percentchange": -15.454547,
        "volume": 50073,
        "openinterest": 15082,
        "impliedvolatility": 0.813478427734375,
        "stk_price_chg": -1.4699999999999989,
        "stk_price_avg_30d": 113.37666666666667,
        "stk_price_avg_5d": 113.37666666666667,
        "lastprice_chg": -0.3800000000000001,
        "lastprice_avg_30d": 2.5366666666666666,
        "lastprice_avg_5d": 2.5366666666666666,
        "pct_chg": -28.787878787878796,
        "iv_chg": 0.2895478857421875,
        "iv_avg_5d": 0.6616244775390624,
        "iv_avg_30d": 0.6616244775390624,
        "iv_avg_all": 0.6616244775390624,
        "vol_chg": -8584.0,
        "oi_chg": 7691.0,
        "flag": 0,
        "amnt": 0,
        "voi": 3,
        "flag_name": "voi",
        "moneyness": 0.9786725663716814
    },
    {
        "stock": "$NVDA",
        "type": "\ud83d\udd34P",
        "strike": "$108.0",
        "exp": "03/07/25",
        "gatherdate": "2025-03-07 10:44:55",
        "contractsymbol": "NVDA250307P00108000",
        "stk_price": 110.59,
        "lastprice": 0.33,
        "ask": 0.33,
        "bid": 0.32,
        "change": -0.8399999,
        "percentchange": -71.79487,
        "volume": 75725,
        "openinterest": 19417,
        "impliedvolatility": 0.5273484765625001,
        "stk_price_chg": -1.4699999999999989,
        "stk_price_avg_30d": 113.37666666666667,
        "stk_price_avg_5d": 113.37666666666667,
        "lastprice_chg": -1.0899999999999999,
        "lastprice_avg_30d": 0.75,
        "lastprice_avg_5d": 0.75,
        "pct_chg": -76.76056338028168,
        "iv_chg": -0.40185145019531243,
        "iv_avg_5d": 0.7514673291015624,
        "iv_avg_30d": 0.7514673291015624,
        "iv_avg_all": 0.7514673291015624,
        "vol_chg": 43809.0,
        "oi_chg": 5946.0,
        "flag": 0,
        "amnt": 0,
        "voi": 3,
        "flag_name": "voi",
        "moneyness": 1.0239814814814816
    },
    {
        "stock": "$IWM",
        "type": "\ud83d\udd34P",
        "strike": "$197.0",
        "exp": "03/10/25",
        "gatherdate": "2025-03-07 10:48:16",
        "contractsymbol": "IWM250310P00197000",
        "stk_price": 203.58,
        "lastprice": 0.14,
        "ask": 0.2,
        "bid": 0.19,
        "change": -0.3,
        "percentchange": -68.18182,
        "volume": 2167,
        "openinterest": 685,
        "impliedvolatility": 0.23242955078125,
        "stk_price_chg": -2.4099999999999966,
        "stk_price_avg_30d": 205.9666666666667,
        "stk_price_avg_5d": 205.9666666666667,
        "lastprice_chg": -0.48,
        "lastprice_avg_30d": 0.44,
        "lastprice_avg_5d": 0.44,
        "pct_chg": -77.41935483870968,
        "iv_chg": -0.14379739013671877,
        "iv_avg_5d": 0.3179592944335938,
        "iv_avg_30d": 0.3179592944335938,
        "iv_avg_all": 0.3179592944335938,
        "vol_chg": 2050.0,
        "oi_chg": 40.0,
        "flag": 0,
        "amnt": 0,
        "voi": 3,
        "flag_name": "voi",
        "moneyness": 1.0334010152284265
    },
    {
        "stock": "$GLD",
        "type": "\ud83d\udfe2C",
        "strike": "$272.0",
        "exp": "04/17/25",
        "gatherdate": "2025-03-07 10:49:25",
        "contractsymbol": "GLD250417C00272000",
        "stk_price": 268.61,
        "lastprice": 5.35,
        "ask": 5.3,
        "bid": 5.2,
        "change": 0.8499999,
        "percentchange": 18.888887,
        "volume": 1543,
        "openinterest": 415,
        "impliedvolatility": 0.18680622772216798,
        "stk_price_chg": -0.39999999999997726,
        "stk_price_avg_30d": 268.9433333333333,
        "stk_price_avg_5d": 268.9433333333333,
        "lastprice_chg": 0.5899999999999999,
        "lastprice_avg_30d": 5.036666666666666,
        "lastprice_avg_5d": 5.036666666666666,
        "pct_chg": 12.394957983193274,
        "iv_chg": 0.021209504699707005,
        "iv_avg_5d": 0.17390759368896488,
        "iv_avg_30d": 0.17390759368896488,
        "iv_avg_all": 0.17390759368896488,
        "vol_chg": 1538.0,
        "oi_chg": 4.0,
        "flag": 0,
        "amnt": 0,
        "voi": 3,
        "flag_name": "voi",
        "moneyness": 0.9875367647058824
    },
    {
        "stock": "$AAPL",
        "type": "\ud83d\udd34P",
        "strike": "$237.5",
        "exp": "03/07/25",
        "gatherdate": "2025-03-07 10:29:39",
        "contractsymbol": "AAPL250307P00237500",
        "stk_price": 238.09,
        "lastprice": 1.07,
        "ask": 1.07,
        "bid": 1.06,
        "change": -2.35,
        "percentchange": -68.71345,
        "volume": 11021,
        "openinterest": 3813,
        "impliedvolatility": 0.270515107421875,
        "stk_price_chg": 4.110000000000014,
        "stk_price_avg_30d": 236.10666666666665,
        "stk_price_avg_5d": 236.10666666666665,
        "lastprice_chg": -3.62,
        "lastprice_avg_30d": 3.3033333333333332,
        "lastprice_avg_5d": 3.3033333333333332,
        "pct_chg": -77.18550106609807,
        "iv_chg": -0.10497941894531249,
        "iv_avg_5d": 0.35930002685546875,
        "iv_avg_30d": 0.35930002685546875,
        "iv_avg_all": 0.35930002685546875,
        "vol_chg": 23.0,
        "oi_chg": -1722.0,
        "flag": 0,
        "amnt": 0,
        "voi": 2,
        "flag_name": "voi",
        "moneyness": 1.0024842105263159
    },
    {
        "stock": "$DKNG",
        "type": "\ud83d\udfe2C",
        "strike": "$43.0",
        "exp": "03/14/25",
        "gatherdate": "2025-03-07 10:31:17",
        "contractsymbol": "DKNG250314C00043000",
        "stk_price": 38.57,
        "lastprice": 0.58,
        "ask": 0.27,
        "bid": 0.24,
        "change": 0.0,
        "percentchange": 0.0,
        "volume": 3284,
        "openinterest": 1414,
        "impliedvolatility": 0.6513706738281251,
        "stk_price_chg": -1.4299999999999997,
        "stk_price_avg_30d": 40.653333333333336,
        "stk_price_avg_5d": 40.653333333333336,
        "lastprice_chg": -0.06000000000000005,
        "lastprice_avg_30d": 0.8966666666666666,
        "lastprice_avg_5d": 0.8966666666666666,
        "pct_chg": -9.375000000000009,
        "iv_chg": -0.002929658203125074,
        "iv_avg_5d": 0.5924519921875001,
        "iv_avg_30d": 0.5924519921875001,
        "iv_avg_all": 0.5924519921875001,
        "vol_chg": 2777.0,
        "oi_chg": 1100.0,
        "flag": 1,
        "amnt": 593,
        "voi": 2,
        "flag_name": "voi",
        "moneyness": 0.8969767441860466
    },
    {
        "stock": "$UPS",
        "type": "\ud83d\udfe2C",
        "strike": "$124.0",
        "exp": "03/14/25",
        "gatherdate": "2025-03-07 10:31:52",
        "contractsymbol": "UPS250314C00124000",
        "stk_price": 120.64,
        "lastprice": 0.45,
        "ask": 0.48,
        "bid": 0.42,
        "change": -0.07999998,
        "percentchange": -15.0943365,
        "volume": 2013,
        "openinterest": 697,
        "impliedvolatility": 0.22705851074218747,
        "stk_price_chg": 1.3599999999999994,
        "stk_price_avg_30d": 119.64,
        "stk_price_avg_5d": 119.64,
        "lastprice_chg": 0.10000000000000003,
        "lastprice_avg_30d": 0.36000000000000004,
        "lastprice_avg_5d": 0.36000000000000004,
        "pct_chg": 28.57142857142858,
        "iv_chg": -0.015136567382812521,
        "iv_avg_5d": 0.23015092773437498,
        "iv_avg_30d": 0.23015092773437498,
        "iv_avg_all": 0.23015092773437498,
        "vol_chg": 1932.0,
        "oi_chg": -48.0,
        "flag": 0,
        "amnt": 0,
        "voi": 2,
        "flag_name": "voi",
        "moneyness": 0.9729032258064516
    },
    {
        "stock": "$MU",
        "type": "\ud83d\udfe2C",
        "strike": "$108.0",
        "exp": "03/28/25",
        "gatherdate": "2025-03-07 10:33:21",
        "contractsymbol": "MU250328C00108000",
        "stk_price": 91.17,
        "lastprice": 1.55,
        "ask": 2.04,
        "bid": 1.98,
        "change": 0.0,
        "percentchange": 0.0,
        "volume": 1060,
        "openinterest": 489,
        "impliedvolatility": 0.789064609375,
        "stk_price_chg": 1.8299999999999983,
        "stk_price_avg_30d": 91.83333333333333,
        "stk_price_avg_5d": 91.83333333333333,
        "lastprice_chg": 0.020000000000000018,
        "lastprice_avg_30d": 1.6600000000000001,
        "lastprice_avg_5d": 1.6600000000000001,
        "pct_chg": 1.3071895424836613,
        "iv_chg": 0.029784858398437364,
        "iv_avg_5d": 0.7395045581054688,
        "iv_avg_30d": 0.7395045581054688,
        "iv_avg_all": 0.7395045581054688,
        "vol_chg": 951.0,
        "oi_chg": 216.0,
        "flag": 1,
        "amnt": 107,
        "voi": 2,
        "flag_name": "voi",
        "moneyness": 0.8441666666666667
    },
    {
        "stock": "$BABA",
        "type": "\ud83d\udd34P",
        "strike": "$141.0",
        "exp": "03/07/25",
        "gatherdate": "2025-03-07 10:35:08",
        "contractsymbol": "BABA250307P00141000",
        "stk_price": 142.76,
        "lastprice": 0.2,
        "ask": 0.23,
        "bid": 0.18,
        "change": -2.37,
        "percentchange": -92.217896,
        "volume": 1711,
        "openinterest": 671,
        "impliedvolatility": 0.278327529296875,
        "stk_price_chg": 4.199999999999989,
        "stk_price_avg_30d": 140.67666666666665,
        "stk_price_avg_5d": 140.67666666666665,
        "lastprice_chg": -3.25,
        "lastprice_avg_30d": 2.5166666666666666,
        "lastprice_avg_5d": 2.5166666666666666,
        "pct_chg": -94.20289855072464,
        "iv_chg": -0.19189261230468757,
        "iv_avg_5d": 0.46916220947265624,
        "iv_avg_30d": 0.46916220947265624,
        "iv_avg_all": 0.46916220947265624,
        "vol_chg": -1549.0,
        "oi_chg": -726.0,
        "flag": 0,
        "amnt": 0,
        "voi": 2,
        "flag_name": "voi",
        "moneyness": 1.012482269503546
    },
    {
        "stock": "$BABA",
        "type": "\ud83d\udd34P",
        "strike": "$143.0",
        "exp": "03/07/25",
        "gatherdate": "2025-03-07 10:35:08",
        "contractsymbol": "BABA250307P00143000",
        "stk_price": 142.76,
        "lastprice": 0.7,
        "ask": 0.74,
        "bid": 0.65,
        "change": -3.2,
        "percentchange": -82.05128,
        "volume": 1502,
        "openinterest": 695,
        "impliedvolatility": 0.20117986328124998,
        "stk_price_chg": 4.199999999999989,
        "stk_price_avg_30d": 140.67666666666665,
        "stk_price_avg_5d": 140.67666666666665,
        "lastprice_chg": -3.95,
        "lastprice_avg_30d": 3.5833333333333335,
        "lastprice_avg_5d": 3.5833333333333335,
        "pct_chg": -84.94623655913979,
        "iv_chg": -0.22070091796875002,
        "iv_avg_5d": 0.4294490649414063,
        "iv_avg_30d": 0.4294490649414063,
        "iv_avg_all": 0.4294490649414063,
        "vol_chg": -110.0,
        "oi_chg": 526.0,
        "flag": 0,
        "amnt": 0,
        "voi": 2,
        "flag_name": "voi",
        "moneyness": 0.9983216783216783
    },
    {
        "stock": "$TSLA",
        "type": "\ud83d\udd34P",
        "strike": "$255.0",
        "exp": "03/07/25",
        "gatherdate": "2025-03-07 10:35:42",
        "contractsymbol": "TSLA250307P00255000",
        "stk_price": 258.44,
        "lastprice": 1.37,
        "ask": 1.37,
        "bid": 1.33,
        "change": -1.08,
        "percentchange": -44.081635,
        "volume": 16395,
        "openinterest": 6494,
        "impliedvolatility": 0.49561051269531253,
        "stk_price_chg": -3.980000000000018,
        "stk_price_avg_30d": 266.51666666666665,
        "stk_price_avg_5d": 266.51666666666665,
        "lastprice_chg": -1.6399999999999997,
        "lastprice_avg_30d": 2.2666666666666666,
        "lastprice_avg_5d": 2.2666666666666666,
        "pct_chg": -54.48504983388703,
        "iv_chg": -0.2824678784179687,
        "iv_avg_5d": 0.769372519938151,
        "iv_avg_30d": 0.769372519938151,
        "iv_avg_all": 0.769372519938151,
        "vol_chg": -15204.0,
        "oi_chg": -423.0,
        "flag": 0,
        "amnt": 0,
        "voi": 2,
        "flag_name": "voi",
        "moneyness": 1.0134901960784313
    },
    {
        "stock": "$XLE",
        "type": "\ud83d\udfe2C",
        "strike": "$92.0",
        "exp": "03/31/25",
        "gatherdate": "2025-03-07 10:40:44",
        "contractsymbol": "XLE250331C00092000",
        "stk_price": 87.32,
        "lastprice": 0.58,
        "ask": 0.57,
        "bid": 0.49,
        "change": 0.19999999,
        "percentchange": 52.631573,
        "volume": 4528,
        "openinterest": 1891,
        "impliedvolatility": 0.23023230712890624,
        "stk_price_chg": 1.25,
        "stk_price_avg_30d": 86.36,
        "stk_price_avg_5d": 86.36,
        "lastprice_chg": 0.23999999999999994,
        "lastprice_avg_30d": 0.42333333333333334,
        "lastprice_avg_5d": 0.42333333333333334,
        "pct_chg": 70.58823529411762,
        "iv_chg": 0.009033112792968756,
        "iv_avg_5d": 0.22681437255859374,
        "iv_avg_30d": 0.22681437255859374,
        "iv_avg_all": 0.22681437255859374,
        "vol_chg": 4509.0,
        "oi_chg": 18.0,
        "flag": 0,
        "amnt": 0,
        "voi": 2,
        "flag_name": "voi",
        "moneyness": 0.9491304347826086
    },
    {
        "stock": "$TLT",
        "type": "\ud83d\udd34P",
        "strike": "$97.0",
        "exp": "03/21/25",
        "gatherdate": "2025-03-07 10:42:53",
        "contractsymbol": "TLT250321P00097000",
        "stk_price": 90.94,
        "lastprice": 6.6,
        "ask": 6.35,
        "bid": 6.25,
        "change": 0.0,
        "percentchange": 0.0,
        "volume": 6846,
        "openinterest": 2903,
        "impliedvolatility": 0.26758544921875,
        "stk_price_chg": 0.45000000000000284,
        "stk_price_avg_30d": 90.7,
        "stk_price_avg_5d": 90.7,
        "lastprice_chg": -0.23000000000000043,
        "lastprice_avg_30d": 6.329999999999999,
        "lastprice_avg_5d": 6.329999999999999,
        "pct_chg": -3.367496339677898,
        "iv_chg": 0.26757544921875,
        "iv_avg_5d": 0.08920181640625001,
        "iv_avg_30d": 0.08920181640625001,
        "iv_avg_all": 0.08920181640625001,
        "vol_chg": 6560.0,
        "oi_chg": -723.0,
        "flag": 0,
        "amnt": 0,
        "voi": 2,
        "flag_name": "voi",
        "moneyness": 0.9375257731958763
    },
    {
        "stock": "$SNAP",
        "type": "\ud83d\udd34P",
        "strike": "$10.0",
        "exp": "03/14/25",
        "gatherdate": "2025-03-07 10:44:46",
        "contractsymbol": "SNAP250314P00010000",
        "stk_price": 9.51,
        "lastprice": 0.47,
        "ask": 0.5,
        "bid": 0.46,
        "change": -0.13000003,
        "percentchange": -21.31148,
        "volume": 1874,
        "openinterest": 728,
        "impliedvolatility": 0.20313296874999998,
        "stk_price_chg": -0.16999999999999993,
        "stk_price_avg_30d": 9.65,
        "stk_price_avg_5d": 9.65,
        "lastprice_chg": -0.08000000000000007,
        "lastprice_avg_30d": 0.5133333333333333,
        "lastprice_avg_5d": 0.5133333333333333,
        "pct_chg": -14.545454545454556,
        "iv_chg": -0.48437015625000013,
        "iv_avg_5d": 0.49740085937500006,
        "iv_avg_30d": 0.49740085937500006,
        "iv_avg_all": 0.49740085937500006,
        "vol_chg": 1629.0,
        "oi_chg": 119.0,
        "flag": 0,
        "amnt": 0,
        "voi": 2,
        "flag_name": "voi",
        "moneyness": 0.951
    },
    {
        "stock": "$CVS",
        "type": "\ud83d\udfe2C",
        "strike": "$66.0",
        "exp": "03/07/25",
        "gatherdate": "2025-03-07 10:46:43",
        "contractsymbol": "CVS250307C00066000",
        "stk_price": 66.18,
        "lastprice": 0.17,
        "ask": 0.21,
        "bid": 0.17,
        "change": -0.08999999,
        "percentchange": -33.333332,
        "volume": 3169,
        "openinterest": 1282,
        "impliedvolatility": 0.06836869140625002,
        "stk_price_chg": 0.8600000000000136,
        "stk_price_avg_30d": 65.90333333333332,
        "stk_price_avg_5d": 65.90333333333332,
        "lastprice_chg": -0.03,
        "lastprice_avg_30d": 0.3766666666666667,
        "lastprice_avg_5d": 0.3766666666666667,
        "pct_chg": -15.0,
        "iv_chg": -0.22363057617187487,
        "iv_avg_5d": 0.23731231445312495,
        "iv_avg_30d": 0.23731231445312495,
        "iv_avg_all": 0.23731231445312495,
        "vol_chg": 2735.0,
        "oi_chg": 6.0,
        "flag": 0,
        "amnt": 0,
        "voi": 2,
        "flag_name": "voi",
        "moneyness": 1.002727272727273
    },
    {
        "stock": "$IWM",
        "type": "\ud83d\udfe2C",
        "strike": "$205.0",
        "exp": "03/07/25",
        "gatherdate": "2025-03-07 10:48:16",
        "contractsymbol": "IWM250307C00205000",
        "stk_price": 203.58,
        "lastprice": 1.04,
        "ask": 1.02,
        "bid": 1.0,
        "change": -1.75,
        "percentchange": -62.724014,
        "volume": 3646,
        "openinterest": 1576,
        "impliedvolatility": 0.38281867187499996,
        "stk_price_chg": -2.4099999999999966,
        "stk_price_avg_30d": 205.9666666666667,
        "stk_price_avg_5d": 205.9666666666667,
        "lastprice_chg": -1.2199999999999998,
        "lastprice_avg_30d": 2.38,
        "lastprice_avg_5d": 2.38,
        "pct_chg": -53.98230088495575,
        "iv_chg": 0.09277250976562501,
        "iv_avg_5d": 0.31006549316406246,
        "iv_avg_30d": 0.31006549316406246,
        "iv_avg_all": 0.31006549316406246,
        "vol_chg": 911.0,
        "oi_chg": 1035.0,
        "flag": 0,
        "amnt": 0,
        "voi": 2,
        "flag_name": "voi",
        "moneyness": 0.9930731707317074
    },
    {
        "stock": "$IWM",
        "type": "\ud83d\udd34P",
        "strike": "$204.0",
        "exp": "03/07/25",
        "gatherdate": "2025-03-07 10:48:16",
        "contractsymbol": "IWM250307P00204000",
        "stk_price": 203.58,
        "lastprice": 0.97,
        "ask": 0.98,
        "bid": 0.94,
        "change": -0.53999996,
        "percentchange": -35.761585,
        "volume": 17097,
        "openinterest": 6615,
        "impliedvolatility": 0.176766044921875,
        "stk_price_chg": -2.4099999999999966,
        "stk_price_avg_30d": 205.9666666666667,
        "stk_price_avg_5d": 205.9666666666667,
        "lastprice_chg": -1.43,
        "lastprice_avg_30d": 1.64,
        "lastprice_avg_5d": 1.64,
        "pct_chg": -59.583333333333336,
        "iv_chg": -0.35473278076171877,
        "iv_avg_5d": 0.3770407348632812,
        "iv_avg_30d": 0.3770407348632812,
        "iv_avg_all": 0.3770407348632812,
        "vol_chg": 9728.0,
        "oi_chg": 3050.0,
        "flag": 0,
        "amnt": 0,
        "voi": 2,
        "flag_name": "voi",
        "moneyness": 0.9979411764705883
    },
    {
        "stock": "$IWM",
        "type": "\ud83d\udfe2C",
        "strike": "$207.0",
        "exp": "03/10/25",
        "gatherdate": "2025-03-07 10:48:16",
        "contractsymbol": "IWM250310C00207000",
        "stk_price": 203.58,
        "lastprice": 1.17,
        "ask": 1.01,
        "bid": 1.0,
        "change": -1.11,
        "percentchange": -48.68421,
        "volume": 1089,
        "openinterest": 523,
        "impliedvolatility": 0.27197993652343744,
        "stk_price_chg": -2.4099999999999966,
        "stk_price_avg_30d": 205.9666666666667,
        "stk_price_avg_5d": 205.9666666666667,
        "lastprice_chg": -0.79,
        "lastprice_avg_30d": 1.9566666666666668,
        "lastprice_avg_5d": 1.9566666666666668,
        "pct_chg": -40.30612244897959,
        "iv_chg": 0.025024163818359313,
        "iv_avg_5d": 0.2526523303222656,
        "iv_avg_30d": 0.2526523303222656,
        "iv_avg_all": 0.2526523303222656,
        "vol_chg": 362.0,
        "oi_chg": 183.0,
        "flag": 0,
        "amnt": 0,
        "voi": 2,
        "flag_name": "voi",
        "moneyness": 0.9834782608695652
    },
    {
        "stock": "$KRE",
        "type": "\ud83d\udfe2C",
        "strike": "$56.0",
        "exp": "03/07/25",
        "gatherdate": "2025-03-07 10:52:37",
        "contractsymbol": "KRE250307C00056000",
        "stk_price": 57.01,
        "lastprice": 2.57,
        "ask": 1.1,
        "bid": 1.06,
        "change": 0.0,
        "percentchange": 0.0,
        "volume": 1510,
        "openinterest": 606,
        "impliedvolatility": 0.34961587890624996,
        "stk_price_chg": -0.45000000000000284,
        "stk_price_avg_30d": 57.81333333333333,
        "stk_price_avg_5d": 57.81333333333333,
        "lastprice_chg": 0.0,
        "lastprice_avg_30d": 2.57,
        "lastprice_avg_5d": 2.57,
        "pct_chg": 0.0,
        "iv_chg": -0.16210775390625004,
        "iv_avg_5d": 0.28711650390625,
        "iv_avg_30d": 0.28711650390625,
        "iv_avg_all": 0.28711650390625,
        "vol_chg": 0.0,
        "oi_chg": 0.0,
        "flag": 0,
        "amnt": 0,
        "voi": 2,
        "flag_name": "voi",
        "moneyness": 1.0180357142857142
    },
    {
        "stock": "$AVGO",
        "type": "\ud83d\udfe2C",
        "strike": "$187.5",
        "exp": "03/07/25",
        "gatherdate": "2025-03-07 10:52:48",
        "contractsymbol": "AVGO250307C00187500",
        "stk_price": 184.54,
        "lastprice": 1.82,
        "ask": 1.84,
        "bid": 1.83,
        "change": -2.98,
        "percentchange": -62.083332,
        "volume": 4654,
        "openinterest": 1828,
        "impliedvolatility": 0.7973653076171875,
        "stk_price_chg": 4.789999999999992,
        "stk_price_avg_30d": 185.79333333333332,
        "stk_price_avg_5d": 185.79333333333332,
        "lastprice_chg": -3.5699999999999994,
        "lastprice_avg_30d": 6.086666666666667,
        "lastprice_avg_5d": 6.086666666666667,
        "pct_chg": -66.23376623376622,
        "iv_chg": -0.7548830249023436,
        "iv_avg_5d": 1.174481965332031,
        "iv_avg_30d": 1.174481965332031,
        "iv_avg_all": 1.174481965332031,
        "vol_chg": 1943.0,
        "oi_chg": 875.0,
        "flag": 0,
        "amnt": 0,
        "voi": 2,
        "flag_name": "voi",
        "moneyness": 0.9842133333333333
    },
    {
        "stock": "$AVGO",
        "type": "\ud83d\udfe2C",
        "strike": "$195.0",
        "exp": "03/07/25",
        "gatherdate": "2025-03-07 10:52:48",
        "contractsymbol": "AVGO250307C00195000",
        "stk_price": 184.54,
        "lastprice": 0.37,
        "ask": 0.36,
        "bid": 0.35,
        "change": -2.33,
        "percentchange": -86.2963,
        "volume": 16034,
        "openinterest": 7847,
        "impliedvolatility": 0.804689453125,
        "stk_price_chg": 4.789999999999992,
        "stk_price_avg_30d": 185.79333333333332,
        "stk_price_avg_5d": 185.79333333333332,
        "lastprice_chg": -2.58,
        "lastprice_avg_30d": 3.606666666666667,
        "lastprice_avg_5d": 3.606666666666667,
        "pct_chg": -87.45762711864407,
        "iv_chg": -0.7197269873046874,
        "iv_avg_5d": 1.180097159423828,
        "iv_avg_30d": 1.180097159423828,
        "iv_avg_all": 1.180097159423828,
        "vol_chg": 10206.0,
        "oi_chg": 1745.0,
        "flag": 0,
        "amnt": 0,
        "voi": 2,
        "flag_name": "voi",
        "moneyness": 0.9463589743589743
    },
    {
        "stock": "$AVGO",
        "type": "\ud83d\udfe2C",
        "strike": "$200.0",
        "exp": "03/07/25",
        "gatherdate": "2025-03-07 10:52:48",
        "contractsymbol": "AVGO250307C00200000",
        "stk_price": 184.54,
        "lastprice": 0.13,
        "ask": 0.14,
        "bid": 0.13,
        "change": -1.57,
        "percentchange": -91.27907,
        "volume": 25560,
        "openinterest": 11077,
        "impliedvolatility": 0.86914193359375,
        "stk_price_chg": 4.789999999999992,
        "stk_price_avg_30d": 185.79333333333332,
        "stk_price_avg_5d": 185.79333333333332,
        "lastprice_chg": -1.79,
        "lastprice_avg_30d": 2.4833333333333334,
        "lastprice_avg_5d": 2.4833333333333334,
        "pct_chg": -93.22916666666667,
        "iv_chg": -0.63867302734375,
        "iv_avg_5d": 1.1855494986979167,
        "iv_avg_30d": 1.1855494986979167,
        "iv_avg_all": 1.1855494986979167,
        "vol_chg": 8232.0,
        "oi_chg": 4737.0,
        "flag": 0,
        "amnt": 0,
        "voi": 2,
        "flag_name": "voi",
        "moneyness": 0.9227
    },
    {
        "stock": "$AVGO",
        "type": "\ud83d\udd34P",
        "strike": "$180.0",
        "exp": "03/07/25",
        "gatherdate": "2025-03-07 10:52:48",
        "contractsymbol": "AVGO250307P00180000",
        "stk_price": 184.54,
        "lastprice": 0.95,
        "ask": 0.99,
        "bid": 0.95,
        "change": -7.55,
        "percentchange": -88.82353,
        "volume": 15807,
        "openinterest": 6036,
        "impliedvolatility": 0.69336244140625,
        "stk_price_chg": 4.789999999999992,
        "stk_price_avg_30d": 185.79333333333332,
        "stk_price_avg_5d": 185.79333333333332,
        "lastprice_chg": -7.47,
        "lastprice_avg_30d": 4.54,
        "lastprice_avg_5d": 4.54,
        "pct_chg": -88.71733966745843,
        "iv_chg": -0.8666983520507812,
        "iv_avg_5d": 1.2120796069335935,
        "iv_avg_30d": 1.2120796069335935,
        "iv_avg_all": 1.2120796069335935,
        "vol_chg": 10307.0,
        "oi_chg": 2180.0,
        "flag": 0,
        "amnt": 0,
        "voi": 2,
        "flag_name": "voi",
        "moneyness": 1.0252222222222223
    },
    {
        "stock": "$SOFI",
        "type": "\ud83d\udfe2C",
        "strike": "$12.5",
        "exp": "03/07/25",
        "gatherdate": "2025-03-07 10:53:10",
        "contractsymbol": "SOFI250307C00012500",
        "stk_price": 12.21,
        "lastprice": 0.14,
        "ask": 0.14,
        "bid": 0.11,
        "change": -0.11,
        "percentchange": -44.0,
        "volume": 3744,
        "openinterest": 1773,
        "impliedvolatility": 0.945313046875,
        "stk_price_chg": -0.23999999999999844,
        "stk_price_avg_30d": 12.69,
        "stk_price_avg_5d": 12.69,
        "lastprice_chg": -0.14,
        "lastprice_avg_30d": 0.4266666666666667,
        "lastprice_avg_5d": 0.4266666666666667,
        "pct_chg": -50.0,
        "iv_chg": 0.16015464843749994,
        "iv_avg_5d": 0.5768271484374999,
        "iv_avg_30d": 0.5768271484374999,
        "iv_avg_all": 0.5768271484374999,
        "vol_chg": 1191.0,
        "oi_chg": 359.0,
        "flag": 0,
        "amnt": 0,
        "voi": 2,
        "flag_name": "voi",
        "moneyness": 0.9768000000000001
    },
    {
        "stock": "$ORCL",
        "type": "\ud83d\udd34P",
        "strike": "$149.0",
        "exp": "03/07/25",
        "gatherdate": "2025-03-07 10:56:18",
        "contractsymbol": "ORCL250307P00149000",
        "stk_price": 151.01,
        "lastprice": 0.35,
        "ask": 0.4,
        "bid": 0.33,
        "change": -1.3199999,
        "percentchange": -79.041916,
        "volume": 1010,
        "openinterest": 346,
        "impliedvolatility": 0.36133451171875,
        "stk_price_chg": 0.8299999999999841,
        "stk_price_avg_30d": 154.20666666666668,
        "stk_price_avg_5d": 154.20666666666668,
        "lastprice_chg": -1.4100000000000001,
        "lastprice_avg_30d": 0.7666666666666666,
        "lastprice_avg_5d": 0.7666666666666666,
        "pct_chg": -80.11363636363637,
        "iv_chg": -0.15478360839843752,
        "iv_avg_5d": 0.4624077197265625,
        "iv_avg_30d": 0.4624077197265625,
        "iv_avg_all": 0.4624077197265625,
        "vol_chg": 860.0,
        "oi_chg": 54.0,
        "flag": 0,
        "amnt": 0,
        "voi": 2,
        "flag_name": "voi",
        "moneyness": 1.013489932885906
    }
]